Metadata-Version: 2.1
Name: pypawn-annotations
Version: 1.0.0.2
Summary: pypawn-annotations
Home-page: https://github.com/bonkibon-education/pypawn-annotation
Download-URL: https://github.com/bonkibon-education/pypawn-annotations/archive/refs/tags/1.0.0.zip
Author: bonkibon
Author-email: bonkibon75@gmail.com
License: GPL-3.0 license, see LICENSE file
Classifier: Programming Language :: Python :: 3
Classifier: Operating System :: OS Independent
Classifier: Intended Audience :: Developers
License-File: LICENSE
